{
    "tags": [
        {
            "ID": 1,
            "pose": {
                "translation": {
                    "x": 16.090899999999998,
                    "y": 0.36829999999999996,
                    "z": 0.127
                },
                "rotation": {
                    "quaternion": {
                        "W": 0.38268343236508984,
                        "X": 0.0,
                        "Y": 0.0,
                        "Z": 0.9238795325112867
                    }
                }
            }
        },
        {
            "ID": 2,
            "pose": {
                "translation": {
                    "x": 0.36829999999999996,
                    "y": 7.8613,
                    "z": 0.127
                },
                "rotation": {
                    "quaternion": {
                        "W": -0.9238795325112867,
                        "X": -0.0,
                        "Y": 0.0,
                        "Z": 0.3826834323650899
                    }
                }
            }
        },
        {
            "ID": 3,
            "pose": {
                "translation": {
                    "x": 16.090899999999998,
                    "y": 0.36829999999999996,
                    "z": 1.0795
                },
                "rotation": {
                    "quaternion": {
                        "W": 0.38268343236508984,
                        "X": 0.0,
                        "Y": 0.0,
                        "Z": 0.9238795325112867
                    }
                }
            }
        },
        {
            "ID": 4,
            "pose": {
                "translation": {
                    "x": 0.36829999999999996,
                    "y": 7.8613,
                    "z": 1.0795
                },
                "rotation": {
                    "quaternion": {
                        "W": -0.9238795325112867,
                        "X": -0.0,
                        "Y": 0.0,
                        "Z": 0.3826834323650899
                    }
                }
            }
        },
        {
            "ID": 5,
            "pose": {
                "translation": {
                    "x": 10.5537,
                    "y": 8.128,
                    "z": 0.127
                },
                "rotation": {
                    "quaternion": {
                        "W": -0.7071067811865475,
                        "X": -0.0,
                        "Y": 0.0,
                        "Z": 0.7071067811865476
                    }
                }
            }
        },
        {
            "ID": 6,
            "pose": {
                "translation": {
                    "x": 5.9055,
                    "y": 0.1016,
                    "z": 0.127
                },
                "rotation": {
                    "quaternion": {
                        "W": 0.7071067811865476,
                        "X": 0.0,
                        "Y": 0.0,
                        "Z": 0.7071067811865476
                    }
                }
            }
        },
        {
            "ID": 7,
            "pose": {
                "translation": {
                    "x": 12.692888,
                    "y": 5.141976,
                    "z": 0.233172
                },
                "rotation": {
                    "quaternion": {
                        "W": 1.0,
                        "X": 0.0,
                        "Y": 0.0,
                        "Z": 0.0
                    }
                }
            }
        },
        {
            "ID": 8,
            "pose": {
                "translation": {
                    "x": 3.7663119999999997,
                    "y": 3.087624,
                    "z": 0.233172
                },
                "rotation": {
                    "quaternion": {
                        "W": 6.123233995736766e-17,
                        "X": 0.0,
                        "Y": 0.0,
                        "Z": 1.0
                    }
                }
            }
        },
        {
            "ID": 9,
            "pose": {
                "translation": {
                    "x": 12.692888,
                    "y": 2.398776,
                    "z": 0.233172
                },
                "rotation": {
                    "quaternion": {
                        "W": 1.0,
                        "X": 0.0,
                        "Y": 0.0,
                        "Z": 0.0
                    }
                }
            }
        },
        {
            "ID": 10,
            "pose": {
                "translation": {
                    "x": 3.7663119999999997,
                    "y": 5.830824,
                    "z": 0.233172
                },
                "rotation": {
                    "quaternion": {
                        "W": 6.123233995736766e-17,
                        "X": 0.0,
                        "Y": 0.0,
                        "Z": 1.0
                    }
                }
            }
        },
        {
            "ID": 11,
            "pose": {
                "translation": {
                    "x": 12.300711999999999,
                    "y": 5.141976,
                    "z": 0.233172
                },
                "rotation": {
                    "quaternion": {
                        "W": 6.123233995736766e-17,
                        "X": 0.0,
                        "Y": 0.0,
                        "Z": 1.0
                    }
                }
            }
        },
        {
            "ID": 12,
            "pose": {
                "translation": {
                    "x": 4.158488,
                    "y": 3.087624,
                    "z": 0.233172
                },
                "rotation": {
                    "quaternion": {
                        "W": 1.0,
                        "X": 0.0,
                        "Y": 0.0,
                        "Z": 0.0
                    }
                }
            }
        },
        {
            "ID": 13,
            "pose": {
                "translation": {
                    "x": 12.300711999999999,
                    "y": 2.398776,
                    "z": 0.233172
                },
                "rotation": {
                    "quaternion": {
                        "W": 6.123233995736766e-17,
                        "X": 0.0,
                        "Y": 0.0,
                        "Z": 1.0
                    }
                }
            }
        },
        {
            "ID": 14,
            "pose": {
                "translation": {
                    "x": 4.158488,
                    "y": 5.830824,
                    "z": 0.233172
                },
                "rotation": {
                    "quaternion": {
                        "W": 1.0,
                        "X": 0.0,
                        "Y": 0.0,
                        "Z": 0.0
                    }
                }
            }
        }
    ],
    "field": {
        "length": 16.4592,
        "width": 8.2296
    }
}